Metadata-Version: 1.1
Name: WHIPS2
Version: 2.0.0
Summary: Scripts for customized regridding of Level-2 data to Level-3 data
Home-page: http://www.sage.wisc.edu/download/WHIPS/WHIPS.html
Author: Jacob Oberman, Keith Maki, Xiaomeng Jin
Author-email: taholloway@wisc.edu
License: MIT License
Download-URL: http://github.com/Joberman/process_sat/downloads
Platform: UNKNOWN
Classifier: Development Status :: 4 - Beta
Classifier: Intended Audience :: Science/Research
Classifier: Natural Language :: English
Classifier: Programming Language :: Python
